{"cameraMode":{"drawMode":0,"name":"Shaded","section":"Shading Mode"},"sceneLighting":true,"audioPlay":false,"sceneViewState":{"showFog":true,"showMaterialUpdate":false,"showSkybox":true,"showFlares":true,"showImageEffects":true,"showParticleSystems":true},"in2DMode":false,"pivot":{"x":-0.2602715492248535,"y":0.08902233839035034,"z":1.9858654737472535},"rotation":{"x":-0.14930032193660737,"y":-0.14448994398117066,"z":0.022064223885536195,"w":-0.9779360890388489},"size":3.3918709754943849,"orthographic":false}